README.rst
setup.py
vimpyre/__init__.py
vimpyre/bat.py
vimpyre/compat.py
vimpyre/console.py
vimpyre/github.py
vimpyre/util.py
vimpyre.egg-info/PKG-INFO
vimpyre.egg-info/SOURCES.txt
vimpyre.egg-info/dependency_links.txt
vimpyre.egg-info/entry_points.txt
vimpyre.egg-info/not-zip-safe
vimpyre.egg-info/requires.txt
vimpyre.egg-info/top_level.txt