Metadata-Version: 1.0
Name: vimpyre
Version: 0.3.0
Summary: Vim Scripts Manager (use pathogen, git, and python!)
Home-page: UNKNOWN
Author: Daniel Lin
Author-email: linpct@gmail.com
License: UNKNOWN
Keywords: vim scripts manager
Platform: UNKNOWN
